odoo/addons/fieldservice_maintenance/README.rst
odoo/addons/fieldservice_maintenance/__init__.py
odoo/addons/fieldservice_maintenance/__manifest__.py
odoo/addons/fieldservice_maintenance/models/__init__.py
odoo/addons/fieldservice_maintenance/models/fsm_equipment.py
odoo/addons/fieldservice_maintenance/models/fsm_order.py
odoo/addons/fieldservice_maintenance/models/maintenance.py
odoo/addons/fieldservice_maintenance/models/stock.py
odoo/addons/fieldservice_maintenance/readme/CONFIGURE.rst
odoo/addons/fieldservice_maintenance/readme/CONTRIBUTORS.rst
odoo/addons/fieldservice_maintenance/readme/CREDITS.rst
odoo/addons/fieldservice_maintenance/readme/DESCRIPTION.rst
odoo/addons/fieldservice_maintenance/readme/INSTALL.rst
odoo/addons/fieldservice_maintenance/readme/ROADMAP.rst
odoo/addons/fieldservice_maintenance/readme/USAGE.rst
odoo/addons/fieldservice_maintenance/static/description/icon.png
odoo/addons/fieldservice_maintenance/static/description/index.html
odoo/addons/fieldservice_maintenance/views/fsm_equipment_view.xml
odoo/addons/fieldservice_maintenance/views/fsm_order_view.xml
odoo/addons/fieldservice_maintenance/views/maintenance_view.xml
odoo11_addon_fieldservice_maintenance-11.0.0.2.0.dist-info/METADATA
odoo11_addon_fieldservice_maintenance-11.0.0.2.0.dist-info/RECORD
odoo11_addon_fieldservice_maintenance-11.0.0.2.0.dist-info/WHEEL
odoo11_addon_fieldservice_maintenance-11.0.0.2.0.dist-info/top_level.txt
